sqs_mover/__init__.py
sqs_mover/sqs_mover.py
sqs_mover-0.0.2.data/scripts/sqsmover
sqs_mover-0.0.2.dist-info/LICENSE
sqs_mover-0.0.2.dist-info/METADATA
sqs_mover-0.0.2.dist-info/WHEEL
sqs_mover-0.0.2.dist-info/top_level.txt
sqs_mover-0.0.2.dist-info/RECORD
