Metadata-Version: 2.1
Name: sqs-mover
Version: 0.0.2
Summary: Utility for moving message between SQS queues
Home-page: https://github.com/kobybum/py-sqs-mover
Author: Koby Bass
License: UNKNOWN
Platform: UNKNOWN
Requires-Python: >=3.6
Requires-Dist: boto3 (>=1.9.236)
